basic_api/__init__.py
basic_api/exceptions.py
basic_api-0.2.0.dist-info/LICENSE.txt
basic_api-0.2.0.dist-info/METADATA
basic_api-0.2.0.dist-info/WHEEL
basic_api-0.2.0.dist-info/top_level.txt
basic_api-0.2.0.dist-info/RECORD
