Metadata-Version: 2.1
Name: basic-api
Version: 0.2.0
Summary: Basic API client
Home-page: https://github.com/gulducat/basic-api
Author: Daniel Bennett
License: UNKNOWN
Keywords: basic,api,client,basic-api
Platform: UNKNOWN
Classifier: License :: OSI Approved :: MIT License
Classifier: Programming Language :: Python
Classifier: Programming Language :: Python :: 2
Classifier: Programming Language :: Python :: 2.7
Classifier: Programming Language :: Python :: 3
Classifier: Programming Language :: Python :: 3.5
Classifier: Programming Language :: Python :: 3.6
Classifier: Programming Language :: Python :: 3.7
Classifier: Programming Language :: Python :: 3.8
Classifier: Programming Language :: Python :: Implementation :: CPython
Provides-Extra: adapter
Requires-Dist: requests ; extra == 'adapter'
